max_density_segment-1.0.2.dist-info/WHEEL
max_density_segment-1.0.2.dist-info/RECORD
max_density_segment-1.0.2.dist-info/METADATA
max_density_segment-1.0.2.dist-info/licenses/LICENSE
max_density_segment.libs/libstdc++-0d31ccbe.so.6.0.32
max_density_segment.libs/libgcc_s-a0b57c20.so.1
max_density_segment/_core.cpython-312-x86_64-linux-musl.so
max_density_segment/__init__.py
max_density_segment/__init__.pyi
